setup.py
src/digimat/__init__.py
src/digimat.meteosuisse.egg-info/PKG-INFO
src/digimat.meteosuisse.egg-info/SOURCES.txt
src/digimat.meteosuisse.egg-info/dependency_links.txt
src/digimat.meteosuisse.egg-info/namespace_packages.txt
src/digimat.meteosuisse.egg-info/not-zip-safe
src/digimat.meteosuisse.egg-info/requires.txt
src/digimat.meteosuisse.egg-info/top_level.txt
src/digimat/meteosuisse/__init__.py
src/digimat/meteosuisse/meteosuisse.py