Metadata-Version: 1.0
Name: digimat.meteosuisse
Version: 0.0.2
Summary: Digimat Meteosuisse CSV File Decoder for Digimat usage
Home-page: http://www.digimat.ch
Author: Frederic Hess
Author-email: fhess@splust.ch
License: PSF
Platform: UNKNOWN
